pyaxepta/__init__.py
pyaxepta/axepta.py
pyaxepta/signature.py
python_axepta-0.3.0.dist-info/METADATA
python_axepta-0.3.0.dist-info/WHEEL
python_axepta-0.3.0.dist-info/top_level.txt
python_axepta-0.3.0.dist-info/RECORD
